README.md
setup.py
django_rdf_io.egg-info/PKG-INFO
django_rdf_io.egg-info/SOURCES.txt
django_rdf_io.egg-info/dependency_links.txt
django_rdf_io.egg-info/not-zip-safe
django_rdf_io.egg-info/top_level.txt
rdf_io/__init__.py
rdf_io/admin.py
rdf_io/models.py
rdf_io/settings.py
rdf_io/urls.py
rdf_io/wsgi.py
rdf_io/migrations/0001_initial.py
rdf_io/migrations/0002_auto_20170810_2351.py
rdf_io/migrations/0003_auto_20180531_1517.py
rdf_io/migrations/0003_load.py
rdf_io/migrations/__init__.py
rdf_io/protocols/__init__.py
rdf_io/protocols/api.py
rdf_io/protocols/ldp.py
rdf_io/protocols/rdf4j.py
rdf_io/signals/__init__.py
rdf_io/signals/utils.py
rdf_io/tests/__init__.py
rdf_io/tests/test_mappings.py
rdf_io/tests/test_viewspy.py
rdf_io/views/__init__.py
rdf_io/views/manage.py
rdf_io/views/serialize.py