Metadata-Version: 1.0
Name: django-rdf-io
Version: 0.1
Summary: Pluggable application for mapping elements of django models to an external RDF store
Home-page: UNKNOWN
Author: Rob Atkinson
Author-email: rob@metalinkage.com
License: BSD
Platform: UNKNOWN
